[{"faceId":"f8a25f75-ff23-464c-8ad0-06b01a4e1ec5","faceRectangle":{"top":41,"left":28,"width":72,"height":72},"faceAttributes":{"smile":0.946,"headPose":{"pitch":3.1,"roll":-0.9,"yaw":2.8},"gender":"male","age":36.0,"facialHair":{"moustache":0.9,"beard":0.9,"sideburns":0.9},"glasses":"ReadingGlasses","emotion":{"anger":0.0,"contempt":0.001,"disgust":0.0,"fear":0.0,"happiness":0.946,"neutral":0.053,"sadness":0.0,"surprise":0.0},"blur":{"blurLevel":"low","value":0.0},"exposure":{"exposureLevel":"goodExposure","value":0.35},"noise":{"noiseLevel":"low","value":0.0},"makeup":{"eyeMakeup":false,"lipMakeup":false},"accessories":[{"type":"glasses","confidence":0.99}],"occlusion":{"foreheadOccluded":false,"eyeOccluded":false,"mouthOccluded":false},"hair":{"bald":0.58,"invisible":false,"hairColor":[{"color":"brown","confidence":0.97},{"color":"gray","confidence":0.59},{"color":"blond","confidence":0.39},{"color":"black","confidence":0.34},{"color":"red","confidence":0.27},{"color":"other","confidence":0.16}]}}}]